kitn-0.0.0.dist-info/METADATA
kitn-0.0.0.dist-info/WHEEL
kitn-0.0.0.dist-info/license_files/LICENSE
kitn/__init__.py
kitn/kitn_python.abi3.so
kitn-0.0.0.dist-info/RECORD
